mexts/__init__.py
mexts/adain_autoencoder.py
mexts/feature_extractor.py
mexts/function.py
mexts/gen.py
mexts/net.py
mexts/style_features_manipulation.py
mexts/models/decoder.pth
mexts/models/vgg_normalised.pth
mexts-0.1.0.dist-info/LICENSE
mexts-0.1.0.dist-info/METADATA
mexts-0.1.0.dist-info/WHEEL
mexts-0.1.0.dist-info/top_level.txt
mexts-0.1.0.dist-info/RECORD
