Metadata-Version: 2.1
Name: mexts
Version: 0.1.0
Summary: MExTS is a texture synthesis package
Home-page: https://github.com/VillainNumberOne/multi-example-texture-synthesis
Author: Maxim Gorshkov
Author-email: mvgorshkofff@gmail.com
License-File: LICENSE
